ibl/__init__.py
ibl-0.0.6.dist-info/LICENSE
ibl-0.0.6.dist-info/METADATA
ibl-0.0.6.dist-info/WHEEL
ibl-0.0.6.dist-info/top_level.txt
ibl-0.0.6.dist-info/RECORD
