Metadata-Version: 2.1
Name: ibl
Version: 0.0.6
Summary: Python api wrapper for infinity bot list
Home-page: https://ibl.gitbook.io/ibl/
Author: Andromeda
Author-email: bots@rjbot.xyz
License: MIT
Keywords: infinity bot list infinity-bot-list-python-api ibl
Platform: UNKNOWN
Classifier: Development Status :: 5 - Production/Stable
Classifier: Intended Audience :: Developers
Classifier: Operating System :: Microsoft :: Windows :: Windows 10
Classifier: License :: OSI Approved :: MIT License
Classifier: Programming Language :: Python :: 3
Requires-Dist: aiohttp
